{"hopethrive": [{"id": 1250008, "mc": 87, "oc": 13}], "honeyloop": [{"id": 1250412, "mc": 17, "oc": 4}], "hordesofwolves227": [{"id": 1250654, "mc": 260, "oc": 52}], "hosam": [{"id": 1250958, "mc": 196, "oc": 70}], "holdengatsby": [{"id": 1250971, "mc": 20, "oc": 9}], "horrorblerant": [{"id": 1251084, "mc": 35, "oc": 8}], "hotdogstation": [{"id": 1251095, "mc": 22, "oc": 3}], "hoofbro": [{"id": 1251594, "mc": 157, "oc": 39}], "hollytinyhoney": [{"id": 1252005, "mc": 43, "oc": 2}], "holosyte": [{"id": 1252284, "mc": 15, "oc": 7}], "hollowowl": [{"id": 1252326, "mc": 6, "oc": 1}], "hornetribcage": [{"id": 1252726, "mc": 138, "oc": 31}], "hot": [{"id": 1253023, "mc": 19, "oc": 3}], "hoppy0616": [{"id": 1253038, "mc": 9, "oc": 4}], "honzik11148": [{"id": 1253465, "mc": 70, "oc": 33}], "hoshizumashima": [{"id": 1253536, "mc": 194, "oc": 44}], "hoikki": [{"id": 1253670, "mc": 403, "oc": 109}], "honeysorrow": [{"id": 1253731, "mc": 50, "oc": 14}], "hofer7": [{"id": 1253894, "mc": 89, "oc": 15}], "holoisholo": [{"id": 1254411, "mc": 20, "oc": 3}], "hooky014": [{"id": 1254703, "mc": 42, "oc": 9}], "hootiecoo": [{"id": 1255296, "mc": 19, "oc": 7}], "honipear": [{"id": 1255764, "mc": 59, "oc": 19}], "hollyhoodballa": [{"id": 1255985, "mc": 332, "oc": 32}], "hotjuicystepmommyshar69": [{"id": 1257887, "mc": 977, "oc": 24}], "hoptimusprime": [{"id": 1258039, "mc": 3, "oc": 2}], "hopkaplay": [{"id": 1259010, "mc": 70, "oc": 15}], "homeyard": [{"id": 1259097, "mc": 10, "oc": 3}], "homytv": [{"id": 1259161, "mc": 85, "oc": 16}], "hotribena": [{"id": 1259244, "mc": 749, "oc": 119}], "hoshinotera": [{"id": 1259322, "mc": 2254, "oc": 230}], "hokila": [{"id": 1259480, "mc": 324, "oc": 50}], "hotgamerdude": [{"id": 1259613, "mc": 448, "oc": 77}], "hounke": [{"id": 1260299, "mc": 29, "oc": 4}], "honeydrippedsyn": [{"id": 1260562, "mc": 63, "oc": 28}], "houlegion": [{"id": 1260635, "mc": 115, "oc": 34}], "hotline": [{"id": 1261851, "mc": 771, "oc": 140}], "hoodieheff": [{"id": 1262083, "mc": 510, "oc": 61}], "hollowshg": [{"id": 1262528, "mc": 464, "oc": 75}], "horatiusthedwarf": [{"id": 1262682, "mc": 105, "oc": 38}], "homesis12": [{"id": 1263101, "mc": 81, "oc": 7}], "hondo8131": [{"id": 1263647, "mc": 32, "oc": 6}], "hoplasyt": [{"id": 1263985, "mc": 4904, "oc": 574}], "honeybunwarrlor": [{"id": 1264052, "mc": 4179, "oc": 1377}], "hobbs4232": [{"id": 1264414, "mc": 684, "oc": 145}], "hobodevco": [{"id": 1264497, "mc": 736, "oc": 219}], "honey7": [{"id": 1264736, "mc": 104, "oc": 38}], "hommiepen": [{"id": 1265007, "mc": 250, "oc": 36}], "hosttheghost123": [{"id": 1265008, "mc": 23, "oc": 6}], "hounc": [{"id": 1265361, "mc": 44, "oc": 3}], "honeybunsarega": [{"id": 1265483, "mc": 16443, "oc": 2480}], "holyjsp": [{"id": 1266155, "mc": 140, "oc": 29}], "hotaruvalentine": [{"id": 1266249, "mc": 2, "oc": 0}], "hokeido1": [{"id": 1266636, "mc": 297, "oc": 90}], "hometown9827": [{"id": 1266752, "mc": 22, "oc": 5}], "hoesfavorite": [{"id": 1266769, "mc": 19, "oc": 3}], "houmcz": [{"id": 1267317, "mc": 4516, "oc": 112}], "horton": [{"id": 1267456, "mc": 309, "oc": 68}], "honeycomb9444": [{"id": 1267628, "mc": 33, "oc": 12}], "howza3999": [{"id": 1267742, "mc": 63, "oc": 7}], "hosuk": [{"id": 1268158, "mc": 46, "oc": 6}], "holy2lord": [{"id": 1268381, "mc": 89, "oc": 26}], "horsemeet1": [{"id": 1268714, "mc": 12308, "oc": 1971}], "holo": [{"id": 1268738, "mc": 154, "oc": 14}], "hornemx5": [{"id": 1269036, "mc": 84, "oc": 13}], "hook1975": [{"id": 1269626, "mc": 46, "oc": 13}], "holoprop": [{"id": 1271164, "mc": 179, "oc": 32}], "hondamoba": [{"id": 1271449, "mc": 515, "oc": 32}], "holvey": [{"id": 1271597, "mc": 61, "oc": 4}], "homeworkradio": [{"id": 1272033, "mc": 1170, "oc": 102}], "howeydoodat": [{"id": 1272108, "mc": 3281, "oc": 180}], "hopperwork": [{"id": 1272241, "mc": 39, "oc": 17}], "hohop": [{"id": 1272438, "mc": 125, "oc": 20}], "hollow302": [{"id": 1272643, "mc": 13, "oc": 4}], "hollisrae": [{"id": 1272658, "mc": 52, "oc": 12}], "honamkii": [{"id": 1272963, "mc": 152, "oc": 29}], "hotdogla": [{"id": 1273081, "mc": 990, "oc": 202}], "hollythemayor": [{"id": 1273306, "mc": 706, "oc": 118}], "horrortm": [{"id": 1273818, "mc": 1624, "oc": 342}], "hokubot": [{"id": 1273860, "mc": 22, "oc": 8}], "holys2864": [{"id": 1274770, "mc": 138, "oc": 16}], "hookyonsmith4280": [{"id": 1274788, "mc": 115, "oc": 19}], "hole1583": [{"id": 1275246, "mc": 210, "oc": 37}], "homewardhymn": [{"id": 1275355, "mc": 655, "oc": 115}], "hotjohn1": [{"id": 1275775, "mc": 418, "oc": 75}], "honeycase": [{"id": 1275802, "mc": 1979, "oc": 541}], "honzacon": [{"id": 1275818, "mc": 16331, "oc": 280}], "hollowbirb": [{"id": 1275846, "mc": 13, "oc": 1}], "honeycereal": [{"id": 1276138, "mc": 217, "oc": 48}], "hovasebastian": [{"id": 1276302, "mc": 70, "oc": 14}], "horrozmc": [{"id": 1276875, "mc": 33, "oc": 4}], "hoc": [{"id": 1276956, "mc": 902, "oc": 94}], "holdendev": [{"id": 1277173, "mc": 7197, "oc": 322}], "honevd": [{"id": 1277444, "mc": 27, "oc": 11}], "hourrift": [{"id": 1278552, "mc": 144, "oc": 14}], "hostpoint": [{"id": 1278561, "mc": 374, "oc": 57}], "horia141": [{"id": 1278864, "mc": 6, "oc": 0}], "hooden1": [{"id": 1279284, "mc": 164, "oc": 51}], "hotnsweet": [{"id": 1279696, "mc": 294, "oc": 38}], "hotpinkboot": [{"id": 1280291, "mc": 26, "oc": 13}], "honeyyany": [{"id": 1280321, "mc": 53, "oc": 6}], "hotwitchywife": [{"id": 1280376, "mc": 156, "oc": 44}], "hoshinjosh": [{"id": 1280671, "mc": 220, "oc": 41}], "howwfr": [{"id": 1280698, "mc": 293, "oc": 30}], "hobbydad": [{"id": 1280713, "mc": 140, "oc": 31}], "hotcheesenip": [{"id": 1281039, "mc": 614, "oc": 139}], "hons": [{"id": 1281299, "mc": 1602, "oc": 113}, {"id": 1286197, "mc": 49647, "oc": 2742}], "hopson": [{"id": 1281964, "mc": 1132, "oc": 179}], "howtomakeaturn": [{"id": 1282167, "mc": 36, "oc": 9}], "horumaito": [{"id": 1282310, "mc": 30, "oc": 4}], "hoangquoc0874": [{"id": 1282567, "mc": 3138, "oc": 191}], "hoyuuna": [{"id": 1282587, "mc": 141, "oc": 14}], "howlere": [{"id": 1282992, "mc": 6, "oc": 3}], "howlerawd": [{"id": 1283234, "mc": 1184, "oc": 131}], "homiaoyuen": [{"id": 1283455, "mc": 109, "oc": 46}], "hossamghost": [{"id": 1283599, "mc": 4755, "oc": 118}], "hooli6051": [{"id": 1284477, "mc": 236, "oc": 5}], "honvex": [{"id": 1284623, "mc": 30, "oc": 6}], "howyoufeel": [{"id": 1284794, "mc": 9, "oc": 2}], "hornyvorelover": [{"id": 1285185, "mc": 809, "oc": 64}], "holdonacoalfield": [{"id": 1285365, "mc": 48, "oc": 9}], "hooligin": [{"id": 1285617, "mc": 79, "oc": 27}], "honeyglazedfaun": [{"id": 1285742, "mc": 25, "oc": 5}], "hoshilapine": [{"id": 1285948, "mc": 131, "oc": 48}], "hotdogfontaine": [{"id": 1286080, "mc": 25, "oc": 4}], "hoggr1der": [{"id": 1286158, "mc": 244, "oc": 10}], "hotdognalds1": [{"id": 1286353, "mc": 18, "oc": 2}], "hotfuzy": [{"id": 1286536, "mc": 262, "oc": 89}], "hornylover": [{"id": 1286993, "mc": 105, "oc": 10}], "hoostv": [{"id": 1287242, "mc": 34, "oc": 2}], "holdmysinkhole": [{"id": 1287418, "mc": 5, "oc": 0}], "holster0844": [{"id": 1287483, "mc": 3, "oc": 1}], "holykac": [{"id": 1288084, "mc": 207, "oc": 11}], "hotseflot": [{"id": 1288332, "mc": 363, "oc": 16}], "hoppanoob": [{"id": 1288613, "mc": 21803, "oc": 1575}], "hosairi": [{"id": 1288714, "mc": 5, "oc": 0}], "horse": [{"id": 1288722, "mc": 75, "oc": 10}], "hojithedemon": [{"id": 1289404, "mc": 3, "oc": 1}], "hoshihana": [{"id": 1289531, "mc": 46, "oc": 13}], "hogito": [{"id": 1289537, "mc": 5, "oc": 0}], "horsedancingwithcrow": [{"id": 1289721, "mc": 29, "oc": 9}], "holispider": [{"id": 1291256, "mc": 157, "oc": 6}], "horkerkiin": [{"id": 1291500, "mc": 36, "oc": 16}], "horizell": [{"id": 1291530, "mc": 28, "oc": 7}], "hooded": [{"id": 1290016, "mc": 4, "oc": 2}], "hosslenerve": [{"id": 1290226, "mc": 19, "oc": 1}], "hornymonkeydreamer": [{"id": 1290949, "mc": 39, "oc": 7}]}