{"vngeance": [{"id": 1254912, "mc": 126, "oc": 11}], "vn": [{"id": 1257161, "mc": 14, "oc": 7}, {"id": 1268963, "mc": 138, "oc": 26}, {"id": 1272662, "mc": 510, "oc": 17}, {"id": 1281102, "mc": 27, "oc": 10}, {"id": 1281409, "mc": 16, "oc": 6}, {"id": 1281606, "mc": 33, "oc": 6}, {"id": 1283451, "mc": 468, "oc": 38}, {"id": 1283566, "mc": 14, "oc": 0}, {"id": 1283779, "mc": 127, "oc": 37}, {"id": 1289395, "mc": 6, "oc": 0}], "vntoolgame": [{"id": 1257594, "mc": 1193, "oc": 110}], "vns": [{"id": 1276520, "mc": 254, "oc": 58}], "vnx": [{"id": 1288419, "mc": 5, "oc": 3}]}