{"847": [{"id": 1250161, "mc": 847, "oc": 199}, {"id": 1261682, "mc": 847, "oc": 83}, {"id": 1263132, "mc": 847, "oc": 160}, {"id": 1266586, "mc": 847, "oc": 16}, {"id": 1274257, "mc": 847, "oc": 161}, {"id": 1283966, "mc": 847, "oc": 405}], "841": [{"id": 1250226, "mc": 841, "oc": 294}, {"id": 1250228, "mc": 841, "oc": 66}, {"id": 1252469, "mc": 841, "oc": 7}, {"id": 1260288, "mc": 841, "oc": 36}, {"id": 1269729, "mc": 841, "oc": 37}, {"id": 1275203, "mc": 841, "oc": 527}, {"id": 1278361, "mc": 841, "oc": 140}, {"id": 1278789, "mc": 841, "oc": 19}, {"id": 1280039, "mc": 841, "oc": 158}], "843": [{"id": 1250906, "mc": 843, "oc": 125}, {"id": 1264325, "mc": 843, "oc": 21}, {"id": 1275731, "mc": 843, "oc": 197}, {"id": 1277290, "mc": 843, "oc": 43}], "8465": [{"id": 1250942, "mc": 8465, "oc": 19}], "845": [{"id": 1251413, "mc": 845, "oc": 175}, {"id": 1251590, "mc": 845, "oc": 140}, {"id": 1256806, "mc": 845, "oc": 147}, {"id": 1259714, "mc": 845, "oc": 216}, {"id": 1264696, "mc": 845, "oc": 83}, {"id": 1282453, "mc": 845, "oc": 14}, {"id": 1291136, "mc": 845, "oc": 114}], "84": [{"id": 1251884, "mc": 84, "oc": 13}, {"id": 1252136, "mc": 84, "oc": 19}, {"id": 1252318, "mc": 84, "oc": 14}, {"id": 1252972, "mc": 84, "oc": 15}, {"id": 1253630, "mc": 84, "oc": 11}, {"id": 1253663, "mc": 84, "oc": 11}, {"id": 1253673, "mc": 84, "oc": 21}, {"id": 1253692, "mc": 84, "oc": 13}, {"id": 1254561, "mc": 84, "oc": 33}, {"id": 1255301, "mc": 84, "oc": 24}, {"id": 1255318, "mc": 84, "oc": 18}, {"id": 1256277, "mc": 84, "oc": 41}, {"id": 1256499, "mc": 84, "oc": 12}, {"id": 1256782, "mc": 84, "oc": 11}, {"id": 1256855, "mc": 84, "oc": 13}, {"id": 1256927, "mc": 84, "oc": 23}, {"id": 1257014, "mc": 84, "oc": 6}, {"id": 1257058, "mc": 84, "oc": 19}, {"id": 1257297, "mc": 84, "oc": 19}, {"id": 1258482, "mc": 84, "oc": 9}, {"id": 1258760, "mc": 84, "oc": 26}, {"id": 1259217, "mc": 84, "oc": 17}, {"id": 1259498, "mc": 84, "oc": 9}, {"id": 1260210, "mc": 84, "oc": 18}, {"id": 1260441, "mc": 84, "oc": 16}, {"id": 1260588, "mc": 84, "oc": 30}, {"id": 1261549, "mc": 84, "oc": 32}, {"id": 1261664, "mc": 84, "oc": 21}, {"id": 1262372, "mc": 84, "oc": 17}, {"id": 1262381, "mc": 84, "oc": 19}, {"id": 1262425, "mc": 84, "oc": 21}, {"id": 1263250, "mc": 84, "oc": 10}, {"id": 1263821, "mc": 84, "oc": 8}, {"id": 1264266, "mc": 84, "oc": 16}, {"id": 1264743, "mc": 84, "oc": 4}, {"id": 1265169, "mc": 84, "oc": 8}, {"id": 1265209, "mc": 84, "oc": 37}, {"id": 1265513, "mc": 84, "oc": 17}, {"id": 1265650, "mc": 84, "oc": 13}, {"id": 1265970, "mc": 84, "oc": 8}, {"id": 1266510, "mc": 84, "oc": 17}, {"id": 1266669, "mc": 84, "oc": 31}, {"id": 1266828, "mc": 84, "oc": 15}, {"id": 1266950, "mc": 84, "oc": 25}, {"id": 1267388, "mc": 84, "oc": 3}, {"id": 1267725, "mc": 84, "oc": 7}, {"id": 1267765, "mc": 84, "oc": 19}, {"id": 1267947, "mc": 84, "oc": 36}, {"id": 1268096, "mc": 84, "oc": 16}, {"id": 1268283, "mc": 84, "oc": 7}, {"id": 1269036, "mc": 84, "oc": 13}, {"id": 1269055, "mc": 84, "oc": 13}, {"id": 1269286, "mc": 84, "oc": 13}, {"id": 1269636, "mc": 84, "oc": 11}, {"id": 1269678, "mc": 84, "oc": 17}, {"id": 1270557, "mc": 84, "oc": 16}, {"id": 1270720, "mc": 84, "oc": 23}, {"id": 1272141, "mc": 84, "oc": 12}, {"id": 1272428, "mc": 84, "oc": 4}, {"id": 1272572, "mc": 84, "oc": 26}, {"id": 1272955, "mc": 84, "oc": 21}, {"id": 1273016, "mc": 84, "oc": 13}, {"id": 1273077, "mc": 84, "oc": 15}, {"id": 1274367, "mc": 84, "oc": 23}, {"id": 1274519, "mc": 84, "oc": 22}, {"id": 1274673, "mc": 84, "oc": 39}, {"id": 1274698, "mc": 84, "oc": 7}, {"id": 1274892, "mc": 84, "oc": 7}, {"id": 1275101, "mc": 84, "oc": 9}, {"id": 1275178, "mc": 84, "oc": 1}, {"id": 1275410, "mc": 84, "oc": 17}, {"id": 1275424, "mc": 84, "oc": 9}, {"id": 1275596, "mc": 84, "oc": 8}, {"id": 1275939, "mc": 84, "oc": 22}, {"id": 1277472, "mc": 84, "oc": 22}, {"id": 1277682, "mc": 84, "oc": 16}, {"id": 1278197, "mc": 84, "oc": 20}, {"id": 1278369, "mc": 84, "oc": 19}, {"id": 1278374, "mc": 84, "oc": 14}, {"id": 1278497, "mc": 84, "oc": 15}, {"id": 1278500, "mc": 84, "oc": 34}, {"id": 1278551, "mc": 84, "oc": 38}, {"id": 1279015, "mc": 84, "oc": 7}, {"id": 1279220, "mc": 84, "oc": 6}, {"id": 1279306, "mc": 84, "oc": 33}, {"id": 1279763, "mc": 84, "oc": 10}, {"id": 1279943, "mc": 84, "oc": 20}, {"id": 1281328, "mc": 84, "oc": 39}, {"id": 1281448, "mc": 84, "oc": 8}, {"id": 1281545, "mc": 84, "oc": 26}, {"id": 1281807, "mc": 84, "oc": 4}, {"id": 1282064, "mc": 84, "oc": 9}, {"id": 1282279, "mc": 84, "oc": 16}, {"id": 1282491, "mc": 84, "oc": 11}, {"id": 1282814, "mc": 84, "oc": 20}, {"id": 1283280, "mc": 84, "oc": 9}, {"id": 1283618, "mc": 84, "oc": 8}, {"id": 1283961, "mc": 84, "oc": 23}, {"id": 1284096, "mc": 84, "oc": 29}, {"id": 1284213, "mc": 84, "oc": 4}, {"id": 1284306, "mc": 84, "oc": 3}, {"id": 1284979, "mc": 84, "oc": 4}, {"id": 1285084, "mc": 84, "oc": 15}, {"id": 1285335, "mc": 84, "oc": 47}, {"id": 1285443, "mc": 84, "oc": 7}, {"id": 1285473, "mc": 84, "oc": 28}, {"id": 1285704, "mc": 84, "oc": 27}, {"id": 1286303, "mc": 84, "oc": 26}, {"id": 1287117, "mc": 84, "oc": 24}, {"id": 1288104, "mc": 84, "oc": 7}, {"id": 1288962, "mc": 84, "oc": 15}, {"id": 1289262, "mc": 84, "oc": 9}, {"id": 1291300, "mc": 84, "oc": 16}, {"id": 1290295, "mc": 84, "oc": 1}, {"id": 1290394, "mc": 84, "oc": 13}, {"id": 1290712, "mc": 84, "oc": 29}], "842": [{"id": 1252094, "mc": 842, "oc": 225}], "848": [{"id": 1258782, "mc": 848, "oc": 155}, {"id": 1276166, "mc": 848, "oc": 129}, {"id": 1287582, "mc": 848, "oc": 88}], "8499": [{"id": 1260645, "mc": 8499, "oc": 1264}], "8439": [{"id": 1261432, "mc": 8439, "oc": 1583}], "846": [{"id": 1261764, "mc": 846, "oc": 125}, {"id": 1266886, "mc": 846, "oc": 89}, {"id": 1276068, "mc": 846, "oc": 358}, {"id": 1280257, "mc": 846, "oc": 27}, {"id": 1291094, "mc": 846, "oc": 109}, {"id": 1291268, "mc": 846, "oc": 27}], "849": [{"id": 1261980, "mc": 849, "oc": 4}, {"id": 1264617, "mc": 849, "oc": 123}, {"id": 1278458, "mc": 849, "oc": 149}, {"id": 1280839, "mc": 849, "oc": 27}, {"id": 1290731, "mc": 849, "oc": 153}], "8442": [{"id": 1263455, "mc": 8442, "oc": 1396}], "8453": [{"id": 1274015, "mc": 8453, "oc": 58}], "844": [{"id": 1277766, "mc": 844, "oc": 1}, {"id": 1282940, "mc": 844, "oc": 56}, {"id": 1283858, "mc": 844, "oc": 215}, {"id": 1288078, "mc": 844, "oc": 110}, {"id": 1291028, "mc": 844, "oc": 46}, {"id": 1290569, "mc": 844, "oc": 32}], "8498": [{"id": 1278061, "mc": 8498, "oc": 1164}], "84303": [{"id": 1279643, "mc": 84303, "oc": 4006}], "840": [{"id": 1287138, "mc": 840, "oc": 257}], "8427": [{"id": 1288989, "mc": 8427, "oc": 2216}], "84026": [{"id": 1289013, "mc": 84026, "oc": 1114}], "8431": [{"id": 1290527, "mc": 8431, "oc": 250}]}