{"rev": [{"id": 1254779, "mc": 76, "oc": 32}, {"id": 1256440, "mc": 136, "oc": 45}, {"id": 1264699, "mc": 134, "oc": 19}, {"id": 1271392, "mc": 144, "oc": 12}, {"id": 1286873, "mc": 10506, "oc": 1390}], "rebl": [{"id": 1255222, "mc": 44, "oc": 12}], "red": [{"id": 1255652, "mc": 1370, "oc": 410}, {"id": 1273272, "mc": 379, "oc": 93}, {"id": 1289867, "mc": 2492, "oc": 59}], "rerp": [{"id": 1256819, "mc": 458, "oc": 171}], "ren": [{"id": 1260064, "mc": 690, "oc": 128}], "res": [{"id": 1260190, "mc": 930, "oc": 216}], "reem": [{"id": 1264855, "mc": 160, "oc": 53}], "rekr": [{"id": 1265600, "mc": 8682, "oc": 1018}], "rek": [{"id": 1265781, "mc": 81, "oc": 20}], "revn": [{"id": 1267761, "mc": 771, "oc": 151}], "rey": [{"id": 1268956, "mc": 317, "oc": 57}], "rein": [{"id": 1272367, "mc": 353, "oc": 37}], "rest": [{"id": 1275130, "mc": 865, "oc": 238}], "rep": [{"id": 1275210, "mc": 46721, "oc": 701}], "rex": [{"id": 1276221, "mc": 6199, "oc": 1354}], "re": [{"id": 1279370, "mc": 2794, "oc": 125}, {"id": 1287240, "mc": 2424, "oc": 634}], "remi": [{"id": 1282436, "mc": 12583, "oc": 171}], "relm": [{"id": 1286272, "mc": 4771, "oc": 561}], "reee": [{"id": 1286630, "mc": 23353, "oc": 2691}], "rett": [{"id": 1286874, "mc": 150, "oc": 9}], "rec": [{"id": 1287026, "mc": 144, "oc": 31}], "req": [{"id": 1291191, "mc": 16876, "oc": 2743}]}