{"kitty": [{"id": 1250546, "mc": 31, "oc": 16}, {"id": 1269641, "mc": 70, "oc": 23}, {"id": 1279454, "mc": 32, "oc": 13}], "kier": [{"id": 1252643, "mc": 68, "oc": 11}], "kidnapper": [{"id": 1254065, "mc": 145, "oc": 26}], "kingdom": [{"id": 1258331, "mc": 124, "oc": 19}, {"id": 1267045, "mc": 56, "oc": 1}, {"id": 1270143, "mc": 431, "oc": 57}, {"id": 1277464, "mc": 168, "oc": 16}, {"id": 1287223, "mc": 662, "oc": 203}, {"id": 1289740, "mc": 196, "oc": 60}], "kickclubnet": [{"id": 1262614, "mc": 1214, "oc": 68}], "kick": [{"id": 1263022, "mc": 31858, "oc": 1567}, {"id": 1279456, "mc": 102, "oc": 18}], "kia": [{"id": 1270382, "mc": 355, "oc": 39}], "kill": [{"id": 1271003, "mc": 778, "oc": 167}, {"id": 1289161, "mc": 263, "oc": 28}], "kid": [{"id": 1274112, "mc": 151, "oc": 10}, {"id": 1279224, "mc": 146, "oc": 30}], "kitt": [{"id": 1277297, "mc": 30, "oc": 4}], "kitten": [{"id": 1277297, "mc": 30, "oc": 4}], "killer": [{"id": 1277519, "mc": 554, "oc": 98}], "king": [{"id": 1277519, "mc": 554, "oc": 98}], "kind": [{"id": 1282489, "mc": 2, "oc": 0}], "kiosk": [{"id": 1286581, "mc": 3829, "oc": 120}], "kitakami": [{"id": 1287012, "mc": 101, "oc": 22}], "kin": [{"id": 1288834, "mc": 78, "oc": 20}]}