{"u7x38m": [{"id": 1250025, "mc": 60, "oc": 6}], "u7c4mrk3gh": [{"id": 1250269, "mc": 8, "oc": 1}], "u7pfacusw4": [{"id": 1250702, "mc": 615, "oc": 49}], "u78pnrt9hp": [{"id": 1276323, "mc": 37, "oc": 11}], "u7kpnewk9x": [{"id": 1276327, "mc": 130, "oc": 6}], "u7bfefp": [{"id": 1276328, "mc": 74, "oc": 7}], "u7ua546yp5": [{"id": 1276330, "mc": 234, "oc": 11}], "u7xv6cevsb": [{"id": 1276332, "mc": 23, "oc": 5}], "u7q6sxcrdn": [{"id": 1276333, "mc": 15, "oc": 3}], "u7vm2afcqh": [{"id": 1276521, "mc": 529, "oc": 90}], "u7dyscq5ky": [{"id": 1276527, "mc": 53, "oc": 8}], "u7hdaxrdhj": [{"id": 1276706, "mc": 41, "oc": 9}], "u74f6cutpr": [{"id": 1276978, "mc": 680, "oc": 169}], "u7trdxqdny": [{"id": 1288029, "mc": 1, "oc": 0}], "u7wsrb7rkc": [{"id": 1288030, "mc": 260, "oc": 57}], "u7kumzhnnd": [{"id": 1288031, "mc": 363, "oc": 55}], "u7fhbv3amv": [{"id": 1288032, "mc": 2006, "oc": 141}], "u7mw6fm": [{"id": 1288033, "mc": 732, "oc": 21}], "u7kkeptyc6": [{"id": 1288039, "mc": 153, "oc": 27}], "u7gnqtsgh": [{"id": 1288261, "mc": 57, "oc": 38}]}