{"wv4zz9m": [{"id": 1255211, "mc": 15, "oc": 6}], "wv9kynjtsw": [{"id": 1255216, "mc": 2, "oc": 0}], "wvejtrqmev": [{"id": 1255217, "mc": 41, "oc": 13}], "wvcbtenzvg": [{"id": 1255226, "mc": 12, "oc": 6}], "wvusdtm": [{"id": 1255240, "mc": 108, "oc": 28}], "wvvpt3dc3a": [{"id": 1255241, "mc": 159, "oc": 17}], "wvzcb4qkfm": [{"id": 1255242, "mc": 57, "oc": 18}], "wv3kd2yhxw": [{"id": 1255244, "mc": 8, "oc": 2}], "wv7xdmyr4u": [{"id": 1255247, "mc": 24, "oc": 4}], "wvhqxv2sya": [{"id": 1255262, "mc": 2, "oc": 0}], "wvcn4a6": [{"id": 1255266, "mc": 16, "oc": 1}], "wvfbnvqrka": [{"id": 1255270, "mc": 15, "oc": 6}], "wvgrexnktp": [{"id": 1255277, "mc": 20, "oc": 6}], "wv424swbpa": [{"id": 1255286, "mc": 15, "oc": 4}], "wvwndfwgk": [{"id": 1255288, "mc": 109, "oc": 34}], "wvzuhn8uxd": [{"id": 1255293, "mc": 1899, "oc": 292}], "wv4fssws8x": [{"id": 1255296, "mc": 19, "oc": 7}], "wv6gmxjnf7": [{"id": 1255297, "mc": 283, "oc": 148}], "wvtzfyjnjm": [{"id": 1255312, "mc": 16, "oc": 9}], "wvjzux6": [{"id": 1255332, "mc": 317, "oc": 88}], "wvtt8n3": [{"id": 1255340, "mc": 627, "oc": 82}], "wvw9gmussz": [{"id": 1255361, "mc": 50, "oc": 9}], "wvfy54ejst": [{"id": 1255365, "mc": 18, "oc": 4}], "wvdpp65cxe": [{"id": 1255367, "mc": 17, "oc": 0}], "wvvw7hunuj": [{"id": 1255379, "mc": 67, "oc": 9}], "wvyctjuna6": [{"id": 1255397, "mc": 34, "oc": 1}], "wvybjasgth": [{"id": 1255399, "mc": 102, "oc": 20}], "wvhttc66uz": [{"id": 1255411, "mc": 65, "oc": 10}], "wvtffqkgge": [{"id": 1255441, "mc": 42, "oc": 13}], "wvmmmwmcaf": [{"id": 1255442, "mc": 124, "oc": 38}], "wvzp95mrvy": [{"id": 1255450, "mc": 102, "oc": 26}], "wvxbnxk": [{"id": 1255483, "mc": 404, "oc": 52}], "wvn89qunhf": [{"id": 1255506, "mc": 137, "oc": 39}], "wvqnvvbre4": [{"id": 1255508, "mc": 30, "oc": 12}], "wv5nwhpxyk": [{"id": 1255510, "mc": 204, "oc": 26}], "wvmxms9": [{"id": 1255519, "mc": 200, "oc": 35}], "wv3mv5cnsp": [{"id": 1255555, "mc": 221, "oc": 33}], "wvjdgq6jrc": [{"id": 1255581, "mc": 245, "oc": 44}], "wvg9vgs4cq": [{"id": 1255582, "mc": 3, "oc": 0}], "wvzuwehweg": [{"id": 1255603, "mc": 23, "oc": 6}], "wv45uqbnmc": [{"id": 1255620, "mc": 89, "oc": 7}], "wvarp43gz8": [{"id": 1255680, "mc": 71, "oc": 8}], "wvpcyvwjdn": [{"id": 1255723, "mc": 263, "oc": 33}], "wvhrewwf3e": [{"id": 1255726, "mc": 69, "oc": 25}], "wvgampanyq": [{"id": 1255826, "mc": 190, "oc": 16}], "wvdrveep6r": [{"id": 1255901, "mc": 13, "oc": 2}], "wvqu9j2t6a": [{"id": 1255909, "mc": 23, "oc": 10}], "wvhesdgchr": [{"id": 1255921, "mc": 290, "oc": 6}], "wvwjawydhz": [{"id": 1256009, "mc": 6, "oc": 2}], "wveu3gagku": [{"id": 1256136, "mc": 208, "oc": 18}], "wvdu5yvk7e": [{"id": 1256203, "mc": 4, "oc": 1}], "wvhj44wykk": [{"id": 1256303, "mc": 9, "oc": 7}], "wvmgeu65hu": [{"id": 1256305, "mc": 251, "oc": 37}], "wvmmrvm7jn": [{"id": 1256306, "mc": 75342, "oc": 2831}], "wvuv3jy8my": [{"id": 1256347, "mc": 47, "oc": 21}], "wvh9neuvuf": [{"id": 1256351, "mc": 55, "oc": 18}], "wvjupu6eep": [{"id": 1256352, "mc": 56, "oc": 8}], "wvrcztatdx": [{"id": 1256365, "mc": 13, "oc": 6}], "wvrjrejrzp": [{"id": 1256391, "mc": 15, "oc": 5}], "wvry4fhc9a": [{"id": 1256400, "mc": 94, "oc": 35}], "wvzwmcwkyh": [{"id": 1256412, "mc": 80, "oc": 12}], "wvjgkbujeh": [{"id": 1256446, "mc": 113, "oc": 4}], "wvbsvjxn7q": [{"id": 1256462, "mc": 69, "oc": 17}], "wvxzbyur36": [{"id": 1256464, "mc": 107, "oc": 43}], "wvtjs3xqe": [{"id": 1256472, "mc": 19, "oc": 11}], "wvftwcanzn": [{"id": 1256483, "mc": 78, "oc": 24}], "wvmedndqc": [{"id": 1256496, "mc": 11, "oc": 2}], "wvukscvmen": [{"id": 1256501, "mc": 89, "oc": 5}], "wvpvn3xfn4": [{"id": 1256505, "mc": 202, "oc": 59}], "wv355krucc": [{"id": 1256531, "mc": 54, "oc": 11}], "wveevx62sw": [{"id": 1256556, "mc": 5, "oc": 1}], "wvkkhyevh4": [{"id": 1256559, "mc": 67, "oc": 25}], "wvnzfengvp": [{"id": 1256593, "mc": 39, "oc": 5}], "wvfpbp8v7b": [{"id": 1256611, "mc": 26, "oc": 5}], "wv4vqx9vnd": [{"id": 1256614, "mc": 129, "oc": 42}], "wvhfugutfc": [{"id": 1256647, "mc": 1, "oc": 0}], "wvsrkr4uva": [{"id": 1256704, "mc": 2, "oc": 2}], "wvyh549sbu": [{"id": 1256748, "mc": 17, "oc": 2}], "wvqskxkfkb": [{"id": 1256784, "mc": 39, "oc": 15}], "wvys4rq6gb": [{"id": 1256821, "mc": 634, "oc": 124}], "wvdtckxtnw": [{"id": 1256835, "mc": 5, "oc": 2}], "wvrjwbbcah": [{"id": 1256870, "mc": 121, "oc": 36}], "wvcayvvbwy": [{"id": 1257122, "mc": 7, "oc": 5}], "wvzntun": [{"id": 1257180, "mc": 67, "oc": 5}], "wveer2j": [{"id": 1257199, "mc": 121, "oc": 11}], "wv72hcsmkq": [{"id": 1257276, "mc": 44, "oc": 10}], "wv2v5bmhmm": [{"id": 1258425, "mc": 38, "oc": 10}], "wv7s4dp": [{"id": 1277613, "mc": 17, "oc": 4}], "wv2gmdjrwh": [{"id": 1277614, "mc": 18, "oc": 1}], "wv8xvhutbe": [{"id": 1277617, "mc": 1066, "oc": 70}], "wvstfcw4am": [{"id": 1277618, "mc": 20, "oc": 1}], "wvafw7x": [{"id": 1277619, "mc": 75, "oc": 12}], "wvkagmdgp9": [{"id": 1277624, "mc": 100, "oc": 10}], "wvgzgr8gqm": [{"id": 1277627, "mc": 126, "oc": 37}], "wvbyqf8kry": [{"id": 1277630, "mc": 6, "oc": 0}], "wv7eufdsmg": [{"id": 1277857, "mc": 74, "oc": 19}], "wvfa6sn": [{"id": 1277858, "mc": 60, "oc": 13}], "wvbg3bjrbv": [{"id": 1277860, "mc": 446, "oc": 31}], "wvb45u75mb": [{"id": 1277863, "mc": 91, "oc": 9}], "wvjffyj": [{"id": 1277865, "mc": 194, "oc": 51}], "wvvdeac": [{"id": 1277867, "mc": 669, "oc": 126}], "wvpppjq2gj": [{"id": 1277868, "mc": 37, "oc": 3}], "wvk3hmxybf": [{"id": 1277869, "mc": 103, "oc": 7}], "wvb5c3c6ez": [{"id": 1277870, "mc": 293, "oc": 37}], "wvfhcqn": [{"id": 1277871, "mc": 21, "oc": 8}], "wvtb8uqqb3": [{"id": 1277873, "mc": 293, "oc": 25}], "wvnbhdn": [{"id": 1277886, "mc": 67, "oc": 17}], "wvwyutqmtp": [{"id": 1278069, "mc": 11, "oc": 8}], "wv7vyngczn": [{"id": 1278205, "mc": 214, "oc": 37}], "wvd92egere": [{"id": 1278556, "mc": 113, "oc": 10}], "wvkmgfvywh": [{"id": 1278814, "mc": 6, "oc": 1}], "wv2kvnz7sj": [{"id": 1289464, "mc": 643, "oc": 56}], "wvhnqpy9ub": [{"id": 1289465, "mc": 17, "oc": 1}], "wvcjxgkadx": [{"id": 1289471, "mc": 3, "oc": 0}], "wvgneyndny": [{"id": 1289479, "mc": 56, "oc": 8}], "wvyvnxkapa": [{"id": 1289614, "mc": 163, "oc": 17}], "wvc2v944hz": [{"id": 1289657, "mc": 1546, "oc": 73}], "wvfnxaaeau": [{"id": 1289705, "mc": 11, "oc": 5}], "wvvdpnzk9u": [{"id": 1289706, "mc": 116, "oc": 28}], "wvkqyhukqe": [{"id": 1289780, "mc": 70, "oc": 16}], "wvhaaumsgc": [{"id": 1289849, "mc": 327, "oc": 18}], "wvavac3rvb": [{"id": 1289881, "mc": 611, "oc": 133}], "wvf99etrzg": [{"id": 1289938, "mc": 313, "oc": 36}], "wvvpdqgtkn": [{"id": 1289979, "mc": 359, "oc": 55}], "wvkybpxhgw": [{"id": 1289987, "mc": 288, "oc": 39}], "wvmbsckfxm": [{"id": 1290064, "mc": 83, "oc": 19}], "wv3qawnefe": [{"id": 1290104, "mc": 80, "oc": 30}], "wv8mb5m5yp": [{"id": 1290122, "mc": 86, "oc": 23}], "wv3rfeh": [{"id": 1290133, "mc": 2155, "oc": 160}], "wv4rtwtqyg": [{"id": 1290285, "mc": 39, "oc": 13}], "wvmgdpktpg": [{"id": 1290376, "mc": 3009, "oc": 163}]}